Workbook

Sheet Main
B2: PL | E2: Shareholders | F2: % Out | H2: Insiders | I2: Shares | J2: % Out | L2: Management | M2: Role | N2: Comment
B3: Last Update | C3: 45971 | E3: Alphabet | F3: =31.942641/$C$7 -> 0.10377746 | H3: 1.84% % of Shares Held by All Insider | L3: Dr. William Spencer Marshall | M3: Co-Founder & CEO | N3: Scientist, NASA Background, PHD in Physics
C4: 0.60555556 | E4: Blackrock | F4: =20.231246/$C$7 -> 0.065728668 | L4: Ms. Ashley Whitfield Fieglein Johnson | M4: President & CFO
E5: Vanguard | F5: =19.358515/$C$7 -> 0.062893279 | L5: Mr. Robert Henry Schingler Jr. | M5: Co-Founnder & C Strategy Officer | N5: 9y NASA, Eng.Physics
B6: Price | C6: 36.9 | E6: DE Shaw | F6: =10.204/$C$7 -> 0.033151459 | L6: Kevin Kirn | M6: CTO
B7: Shares | C7: =Model!V28 -> 307.79942 | E7: Driehaus Capital | F7: =8.511/$C$7 -> 0.027651124 | L7: Christopher Geualdi | M7: IR
B8: MC | C8: =C6*C7 -> 11357.799 | E8: Canda Pension plan | F8: =7.905/$C$7 -> 0.025682309 | L8: Thomas Murphy | M8: Counsel
B9: CASH | C9: =Model!V46+Model!V48 -> 640.09 | E9: Jane Street | F9: =7.83/$C$7 -> 0.025438644 | L9: Trevor Hammond | M9: CCO
B10: DEBT | C10: =Model!V73 -> 446.884 | E10: Van Eck Associates | F10: =7.6/$C$7 -> 0.024691404 | L10: Katie Penn | M10: Senior Vice President of Marketing
B11: Net CASH | C11: =C9-C10 -> 193.206 | E11: Capricorn Investment | F11: =7.141/$C$7 -> 0.023200173
B12: EV | C12: =C8-C9+C10 -> 11164.593 | E12: State Street | F12: =5.99/$C$7 -> 0.019460725
B13: PE0 | C13: =Main!C6/Model!F29 -> -46.009069 | E13: Geode Capital | F13: =5.702/$C$7 -> 0.018525051
B14: PE1 | C14: =Main!C6/Model!G30 -> -335.45455 | E14: Toronto Dominion | F14: =5.354/$C$7 -> 0.017394445
B15: PE2 | C15: =C6/Model!H30 -> -1845
B16: EG1 | C16: =Model!G30/Model!F29-1 -> -0.86284559
B17: EG2 | C17: =1 -> 1 | E17: Driving business factors: | L17: Planet Labs PBC designs, constructs, and launches constellations of satellites with the intent of providing high cadence geospatial data delivered to customers through an online platform worldwide. The company offers Open Geospatial Consortium, a cloud-native proprietary technology that performs critical processing and overall harmonizing of images for time series and data fusion and analysis; and space-based hardware and related software systems. It serves agriculture, mapping, forestry, and finance and insurance, as well as federal, state, and local government bodies. The company was incorporated in 2010 and is headquartered in San Francisco, California.
B18: PEG1 | C18: =C14/(C16*100) -> 3.8877703
B19: PEG2 | C19: =C15/(C17*100) -> -18.45
B20: RG1 | C20: =Model!G13/Model!F12-1 -> 0.35019027
B21: RG2 | C21: =Model!H13/Model!G13-1 -> 0.33216203
B22: EBIT | C22: =Model!C18+Model!C16 -> 0
B23: EBITDA | C23: =Model!C18 -> 0
B24: Gross Margin | C24: =Model!C22 -> 0
B25: Net Margin | C25: =Model!C23 -> 0
B26: EV/EBITDA | C26: =C12/C23 -> #DIV/0!
B27: Debt to Equity Ratio | C27: =Model!#REF!/Model!#REF! -> #REF! | E27: Notes
B28: Interest Coverage Ratio | C28: =C22/-Model!C16 -> #DIV/0! | E28: Government Revenue flat
B29: Current Ratio | C29: =Model!#REF!/Model!#REF! -> #REF! | E29: Germany and Sweden ocntracts
B30: Quick Ratio | C30: =(Model!#REF!+Model!#REF!)/Model!#REF! -> #REF! | E30: 9 Figure Satellite Services Deal
B31: WC over Total Assets | C31: =(Model!#REF!-Model!#REF!)/Model!#REF! -> #REF! | E31: Moving into profitability 2026
B32: Book Value per Share | C32: =(Model!#REF!-Model!#REF!)/Main!C7 -> #REF! | E32: Moving into positive free cash flow in 2026
B33: Sales to Assets Ratio | C33: =Model!#REF!/Model!#REF! -> #REF!
B34: Returns on Assets | C34: =Model!#REF!/Model!#REF! -> #REF!
B35: ROE | C35: =Model!#REF!/Model!#REF! -> #REF!
B36: FCF Yield

Sheet Model
A1: Main
C2: FY22 | D2: FY23 | E2: FY24 | F2: FY25 | G2: FY26 | H2: FY27 | K2: Q123 | L2: Q223 | M2: Q323 | N2: Q423 | O2: Q124 | P2: Q224 | Q2: Q324 | R2: Q424 | S2: Q125 | T2: Q225 | U2: Q325 | V2: Q425 | W2: Q126 | X2: Q226
B3: North America | D3: 113.526 | E3: 119.35 | F3: 132.01 | O3: 32.713 | P3: 30.797 | Q3: 27.038 | R3: =E3-Q3-P3-O3 -> 28.802 | S3: 29.533 | T3: 31.093 | U3: 35.148 | V3: =F3-U3-T3-S3 -> 36.236
B4: Asia Pacific & Japan | D4: 37.434 | E4: 42.401 | F4: 59.813 | O4: 11.142 | P4: 10.298 | Q4: 10.334 | R4: =E4-Q4-P4-O4 -> 10.627 | S4: 15.307 | T4: 16.15 | U4: 14.324 | V4: =F4-U4-T4-S4 -> 14.032
B5: Europe, Middle East & Afrika | D5: 60.176 | E5: 70.085 | F5: 103.674 | O5: 13.694 | P5: 17.226 | Q5: 20.011 | R5: =E5-Q5-P5-O5 -> 19.154 | S5: 18.849 | T5: 23.467 | U5: 27.613 | V5: =F5-U5-T5-S5 -> 33.745
B6: Latin America | D6: 9.56 | E6: 12.516 | F6: 12.23 | O6: 2.891 | P6: 2.771 | Q6: 3.883 | R6: =E6-Q6-P6-O6 -> 2.971 | S6: 2.576 | T6: 2.676 | U6: 4.169 | V6: =F6-U6-T6-S6 -> 2.809
B9: Civil Government | D9: 60.6 | E9: 71.887 | F9: 71.91 | O9: 18.049 | P9: 17.179 | Q9: 18.552 | R9: =E9-Q9-P9-O9 -> 18.107 | S9: 16.28 | T9: 16.426 | U9: 18.828 | V9: =F9-U9-T9-S9 -> 20.376
B10: Commercial | D10: 65.541 | E10: 56.184 | F10: 55.585 | O10: 12.777 | P10: 14.232 | Q10: 14.173 | R10: =E10-Q10-P10-O10 -> 15.002 | S10: 13.338 | T10: 15.051 | U10: 13.061 | V10: =F10-U10-T10-S10 -> 14.135
B11: Defense & Intelligence | D11: 94.555 | E11: 116.281 | F11: 180.232 | O11: 29.614 | P11: 29.681 | Q11: 28.541 | R11: =E11-Q11-P11-O11 -> 28.445 | S11: 36.647 | T11: 41.909 | U11: 49.365 | V11: =F11-U11-T11-S11 -> 52.311
B12: Revenue | D12: =SUM(D9:D11) -> 220.696 | E12: =SUM(E9:E11) -> 244.352 | F12: =SUM(F9:F11) -> 307.727 | G12: =SUM(G9:G11) -> 0 | K12: =SUM(K9:K11) -> 0 | L12: =SUM(L9:L11) -> 0 | M12: =SUM(M9:M11) -> 0 | N12: =SUM(N9:N11) -> 0 | O12: =SUM(O9:O11) -> 60.44 | P12: =SUM(P9:P11) -> 61.092 | Q12: =SUM(Q9:Q11) -> 61.266 | R12: =SUM(R9:R11) -> 61.554 | ... X12: =SUM(X9:X11) -> 0
B13: Rev. Exp. | G13: 415.49 | H13: 553.5 | W13: 90.1 | X13: 101.34 | Y13: 114 | Z13: 126
B14: COGS Prod1 | D14: 107.746 | E14: 104.627 | F14: 135.242 | O14: 28.757 | P14: 28.782 | Q14: 23.749 | R14: =E14-Q14-P14-O14 -> 23.339 | S14: 29.662 | T14: 31.118 | U14: 34.67 | V14: =F14-U14-T14-S14 -> 39.792
B15: COGS Prod2
B16: COGS Prod3
B17: COGS | C17: =SUM(C14:C16) -> 0 | D17: =SUM(D14:D16) -> 107.746 | E17: =SUM(E14:E16) -> 104.627 | F17: =SUM(F14:F16) -> 135.242 | G17: =SUM(G14:G16) -> 0 | K17: =SUM(K14:K16) -> 0 | L17: =SUM(L14:L16) -> 0 | M17: =SUM(M14:M16) -> 0 | N17: =SUM(N14:N16) -> 0 | O17: =SUM(O14:O16) -> 28.757 | P17: =SUM(P14:P16) -> 28.782 | Q17: =SUM(Q14:Q16) -> 23.749 | R17: =SUM(R14:R16) -> 23.339 | ... X17: =SUM(X14:X16) -> 0
B18: R&D | D18: 116.339 | E18: 101.006 | F18: 106.749 | O18: 25.589 | P18: 27.25 | Q18: 25.216 | R18: =E18-Q18-P18-O18 -> 22.951 | S18: 23.074 | T18: 24.155 | U18: 27.327 | V18: =F18-U18-T18-S18 -> 32.193
B19: S&M | D19: 86.304 | E19: 77.694 | F19: 72.676 | O19: 21.485 | P19: 23.733 | Q19: 16.795 | R19: =E19-Q19-P19-O19 -> 15.681 | S19: 16.314 | T19: 17.574 | U19: 18.783 | V19: =F19-U19-T19-S19 -> 20.005
B20: G&A | D20: 80.055 | E20: 77.147 | F20: 88.133 | O20: 19.18 | P20: 20.904 | Q20: 18.114 | R20: =E20-Q20-P20-O20 -> 18.949 | S20: 19.986 | T20: 18.499 | U20: 18.814 | V20: =F20-U20-T20-S20 -> 30.834
B21: Operational Income | C21: =C12-SUM(C17:C20) -> 0 | D21: =D12-SUM(D17:D20) -> -169.748 | E21: =E12-SUM(E17:E20) -> -116.122 | F21: =F12-SUM(F17:F20) -> -95.073 | G21: =G12-SUM(G17:G20) -> 0 | K21: =K12-SUM(K17:K20) -> 0 | L21: =L12-SUM(L17:L20) -> 0 | M21: =M12-SUM(M17:M20) -> 0 | N21: =N12-SUM(N17:N20) -> 0 | O21: =O12-SUM(O17:O20) -> -34.571 | P21: =P12-SUM(P17:P20) -> -39.577 | Q21: =Q12-SUM(Q17:Q20) -> -22.608 | R21: =R12-SUM(R17:R20) -> -19.366 | ... X21: =X12-SUM(X17:X20) -> 0
B22: Interest Collect (exp) | D22: 15.414 | E22: =10.257-0.832 -> 9.425 | F22: =14.329-3.436 -> 10.893 | O22: 3.107 | P22: =2.771-0.602 -> 2.169 | Q22: =2.414-0.277 -> 2.137 | R22: =E22-Q22-P22-O22 -> 2.012 | S22: 1.884 | T22: =2.172-5.679 -> -3.507 | U22: =4.414-1.02 -> 3.394 | V22: =F22-U22-T22-S22 -> 9.122
B23: Gains on Equity | D23: 13.709 | E23: -15.116 | F23: -161.4 | O23: 1.53 | Q23: 0.198 | R23: =E23-Q23-P23-O23 -> -16.844 | S23: 10.387 | U23: -43.473 | V23: =F23-U23-T23-S23 -> -128.314
B24: Other | D24: 0.931 | E24: 1.077 | F24: 3.375 | O24: 1.083 | P24: -0.363 | Q24: 0.217 | R24: =E24-Q24-P24-O24 -> 0.14 | S24: -1.2 | T24: -0.628 | U24: 0.018 | V24: =F24-U24-T24-S24 -> 5.185
B25: Net Income before Tax | C25: =C21+SUM(C22:C24) -> 0 | D25: =D21+SUM(D22:D24) -> -139.694 | E25: =E21+SUM(E22:E24) -> -120.736 | F25: =F21+SUM(F22:F24) -> -242.205 | G25: =G21+SUM(G22:G24) -> 0 | K25: =K21+SUM(K22:K24) -> 0 | L25: =L21+SUM(L22:L24) -> 0 | M25: =M21+SUM(M22:M24) -> 0 | N25: =N21+SUM(N22:N24) -> 0 | O25: =O21+SUM(O22:O24) -> -28.851 | P25: =P21+SUM(P22:P24) -> -37.771 | Q25: =Q21+SUM(Q22:Q24) -> -20.056 | R25: =R21+SUM(R22:R24) -> -34.058 | ... X25: =X21+SUM(X22:X24) -> 0
B26: Income Tax | D26: 0.815 | E26: 2.46 | F26: 4.655 | O26: 0.442 | P26: 0.897 | Q26: 0.025 | R26: =E26-Q26-P26-O26 -> 1.096 | S26: 0.928 | T26: 0.497 | U26: 0.784 | V26: =F26-U26-T26-S26 -> 2.446
B27: Net Income | C27: =C25-SUM(C26:C26) -> 0 | D27: =D25-SUM(D26:D26) -> -140.509 | E27: =E25-SUM(E26:E26) -> -123.196 | F27: =F25-SUM(F26:F26) -> -246.86 | G27: =G25-SUM(G26:G26) -> 0 | K27: =K25-SUM(K26:K26) -> 0 | L27: =L25-SUM(L26:L26) -> 0 | M27: =M25-SUM(M26:M26) -> 0 | N27: =N25-SUM(N26:N26) -> 0 | O27: =O25-SUM(O26:O26) -> -29.293 | P27: =P25-SUM(P26:P26) -> -38.668 | Q27: =Q25-SUM(Q26:Q26) -> -20.081 | R27: =R25-SUM(R26:R26) -> -35.154 | ... X27: =X25-SUM(X26:X26) -> 0
B28: Shares | D28: 279.5857 | E28: 292.12429 | F28: 307.79942 | O28: 288.26872 | P28: 290.36432 | Q28: 293.33732 | R28: =E28 -> 292.12429 | S28: 300.26795 | T28: 304.1292 | U28: 309.24825 | V28: 307.79942
B29: EPS | C29: =C27/C28 -> #DIV/0! | D29: =D27/D28 -> -0.50256147 | E29: =E27/E28 -> -0.4217246 | F29: =F27/F28 -> -0.8020158 | G29: =G27/G28 -> #DIV/0! | K29: =K27/K28 -> #DIV/0! | L29: =L27/L28 -> #DIV/0! | M29: =M27/M28 -> #DIV/0! | N29: =N27/N28 -> #DIV/0! | O29: =O27/O28 -> -0.10161699 | P29: =P27/P28 -> -0.13317063 | Q29: =Q27/Q28 -> -0.068457023 | R29: =R27/R28 -> -0.12033919 | ... X29: =X27/X28 -> #DIV/0!
B30: EPS exp. | G30: -0.11 | H30: -0.02 | W30: -0.04 | X30: -0.03 | Y30: -0.02 | Z30: -0.01
B31: Gross Margin | C31: =1-C17/C12 -> #DIV/0! | D31: =1-D17/D12 -> 0.51178997 | E31: =1-E17/E12 -> 0.57181852 | F31: =1-F17/F12 -> 0.56051305 | G31: =1-G17/G12 -> #DIV/0! | K31: =1-K17/K12 -> #DIV/0! | L31: =1-L17/L12 -> #DIV/0! | M31: =1-M17/M12 -> #DIV/0! | N31: =1-N17/N12 -> #DIV/0! | O31: =1-O17/O12 -> 0.52420582 | P31: =1-P17/P12 -> 0.52887448 | Q31: =1-Q17/Q12 -> 0.61236248 | R31: =1-R17/R12 -> 0.62083699 | ... X31: =1-X17/X12 -> #DIV/0!
B32: Net Margin | C32: =C27/C12 -> #DIV/0! | D32: =D27/D12 -> -0.6366631 | E32: =E27/E12 -> -0.50417431 | F32: =F27/F12 -> -0.80220455 | G32: =G27/G12 -> #DIV/0! | K32: =K27/K12 -> #DIV/0! | L32: =L27/L12 -> #DIV/0! | M32: =M27/M12 -> #DIV/0! | N32: =N27/N12 -> #DIV/0! | O32: =O27/O12 -> -0.48466248 | P32: =P27/P12 -> -0.63294703 | Q32: =Q27/Q12 -> -0.32776744 | R32: =R27/R12 -> -0.5711083 | ... X32: =X27/X12 -> #DIV/0!
B33: Revenue Growth | D33: =D12/C12-1 -> #DIV/0! | E33: =E12/D12-1 -> 0.10718817 | F33: =F12/E12-1 -> 0.25935945 | G33: =G12/F12-1 -> -1 | S33: =S12/O12-1 -> 0.096376572 | T33: =T12/P12-1 -> 0.20123748 | U33: =U12/Q12-1 -> 0.32624947 | V33: =V12/R12-1 -> 0.41050135 | W33: =W12/S12-1 -> -1 | X33: =X12/T12-1 -> -1
B34: R&D / REV | C34: =C18/C12 -> #DIV/0! | D34: =D18/D12 -> 0.52714594 | E34: =E18/E12 -> 0.41336269 | F34: =F18/F12 -> 0.34689514 | G34: =G18/G12 -> #DIV/0! | K34: =K18/K12 -> #DIV/0! | L34: =L18/L12 -> #DIV/0! | M34: =M18/M12 -> #DIV/0! | N34: =N18/N12 -> #DIV/0! | O34: =O18/O12 -> 0.42337856 | P34: =P18/P12 -> 0.44604858 | Q34: =Q18/Q12 -> 0.41158228 | R34: =R18/R12 -> 0.3728596 | ... X34: =X18/X12 -> #DIV/0!
B35: S&M / REV | C35: =C19/C12 -> #DIV/0! | D35: =D19/D12 -> 0.39105376 | E35: =E18/E12 -> 0.41336269 | F35: =F19/F12 -> 0.23617037 | G35: =G19/G12 -> #DIV/0! | K35: =K19/K12 -> #DIV/0! | L35: =L19/L12 -> #DIV/0! | M35: =M19/M12 -> #DIV/0! | N35: =N19/N12 -> #DIV/0! | O35: =O19/O12 -> 0.35547651 | P35: =P19/P12 -> 0.38847967 | Q35: =Q19/Q12 -> 0.27413247 | R35: =R19/R12 -> 0.25475193 | ... T35: =T19/T12 -> 0.23947347 | U35: =U18/U12 -> 0.33631575 | V35: =V18/V12 -> 0.37079312 | W35: =W19/W12 -> #DIV/0! | X35: =X19/X12 -> #DIV/0!
B36: G&A / REV | D36: =D20/C20-1 -> #DIV/0! | E36: =E20/D20-1 -> -0.036325027 | F36: =F20/E20-1 -> 0.14240346 | Q36: =Q20/P20-1 -> -0.13346728 | R36: =R20/Q20-1 -> 0.046096942 | S36: =S20/R20-1 -> 0.054725843 | T36: =T20/S20-1 -> -0.074402081 | U36: =U20/T20-1 -> 0.017027947 | V36: =V20/U20-1 -> 0.63888594 | W36: =W20/V20-1 -> -1 | X36: =X20/W20-1 -> #DIV/0!
B37: Asia Rev y/y | D37: =D4/C4-1 -> #DIV/0! | E37: =E4/D4-1 -> 0.13268686 | F37: =F4/E4-1 -> 0.41065069 | Q37: =Q4/M4-1 -> #DIV/0! | R37: =R4/N4-1 -> #DIV/0! | S37: =S4/O4-1 -> 0.37381081 | T37: =T4/P4-1 -> 0.56826568 | U37: =U4/Q4-1 -> 0.38610412 | V37: =V4/R4-1 -> 0.32041028 | W37: =W4/S4-1 -> -1 | X37: =X4/T4-1 -> -1
B38: Europe Rev y/y | D38: =D5/C5-1 -> #DIV/0! | E38: =E5/D5-1 -> 0.16466698 | F38: =F5/E5-1 -> 0.4792609 | Q38: =Q5/M5-1 -> #DIV/0! | R38: =R5/N5-1 -> #DIV/0! | S38: =S5/O5-1 -> 0.37644224 | T38: =T5/P5-1 -> 0.36230117 | U38: =U5/Q5-1 -> 0.37989106 | V38: =V5/R5-1 -> 0.761773 | W38: =W5/S5-1 -> -1 | X38: =X5/T5-1 -> -1
B39: Civil Government Revenue y/y | D39: =D9/C9-1 -> #DIV/0! | E39: =E9/D9-1 -> 0.18625413 | F39: =F9/E9-1 -> 0.00031994658 | G39: =G9/F9-1 -> -1 | Q39: =Q9/M9-1 -> #DIV/0! | R39: =R9/N9-1 -> #DIV/0! | S39: =S9/O9-1 -> -0.09801097 | T39: =T9/P9-1 -> -0.043832586 | U39: =U9/Q9-1 -> 0.014877102 | V39: =V9/R9-1 -> 0.12531065 | W39: =W9/S9-1 -> -1 | X39: =X9/T9-1 -> -1
B40: Defense Revenue y/y | D40: =D10/C10-1 -> #DIV/0! | E40: =E10/D10-1 -> -0.1427656 | F40: =F11/E11-1 -> 0.54996947 | G40: =G10/F10-1 -> -1 | Q40: =Q10/M10-1 -> #DIV/0! | R40: =R10/N10-1 -> #DIV/0! | S40: =S10/O10-1 -> 0.04390702 | T40: =T10/P10-1 -> 0.057546374 | U40: =U10/Q10-1 -> -0.078459042 | V40: =V10/R10-1 -> -0.057792294 | W40: =W10/S10-1 -> -1 | X40: =X10/T10-1 -> -1
B41: EPS Growth | C41: =C29/#REF!-1 -> #DIV/0! | D41: =D29/C29-1 -> #DIV/0! | E41: =E29/D29-1 -> -0.16084972 | F41: =F29/E29-1 -> 0.90175246 | G41: =G29/F29-1 -> #DIV/0! | O41: =O27/K27-1 -> #DIV/0! | P41: =P27/L27-1 -> #DIV/0! | Q41: =Q27/M27-1 -> #DIV/0! | R41: =R27/N27-1 -> #DIV/0! | S41: =S27/O27-1 -> -0.56890725 | T41: =T27/P27-1 -> -0.41574428 | U41: =U27/Q27-1 -> 1.9473134 | V41: =V27/R27-1 -> 3.3367753 | ... X41: =X27/T27-1 -> -1
B45: Net Cash | C45: =C46+C48-C73 -> 0 | D45: =D46+D48-D73 -> 0 | E45: =E46+E48-E73 -> 222.075 | F45: =F46+F48-F73 -> 193.206 | G45: =G46+G48-G73 -> 0 | K45: =K46+K48-K73 -> 0 | L45: =L46+L48-L73 -> 0 | M45: =M46+M48-M73 -> 0 | N45: =N46+N48-N73 -> 0 | O45: =O46+O48-O73 -> 0 | P45: =P46+P48-P73 -> 0 | Q45: =Q46+Q48-Q73 -> 0 | R45: =R46+R48-R73 -> 222.075 | ... V45: =V46+V48-V73 -> 193.206 | W45: =W46+W47-W61 -> 0 | X45: =X46+X47-X61 -> 0
B46: Cash | E46: =R46 -> 118.048 | F46: =V46 -> 229.441 | R46: 118.048 | S46: 133.471 | T46: 181.087 | U46: 443.349 | V46: 229.441
B47: Restricted Cash | E47: =R47 -> 6.598 | F47: =V47 -> 0.642 | R47: 6.598 | S47: 6.607 | T47: 6.316 | U47: 0.906 | V47: 0.642
B48: Short-term investments | E48: =R48 -> 104.027 | F48: =V48 -> 410.649 | R48: 104.027 | S48: 92.624 | T48: 90.45 | U48: 233.975 | V48: 410.649
B49: AR | E49: =R49 -> 55.833 | F49: =V49 -> 83.528 | R49: 55.833 | S49: 74.663 | T49: 51.663 | U49: 46.332 | V49: 83.528
B50: Inventorys | E50: =R50 -> 0 | F50: =V50 -> 6.118 | R50: 0 | S50: 0 | V50: 6.118
B51: Prepaid Expense | E51: =R51 -> 17.719 | F51: =V51 -> 44.984 | R51: 17.719 | S51: 17.447 | T51: 25.997 | U51: 29.581 | V51: 44.984
B52: Current Assets | C52: =SUM(C46:C51) -> 0 | D52: =SUM(D46:D51) -> 0 | E52: =SUM(E46:E51) -> 302.225 | F52: =SUM(F46:F51) -> 775.362 | G52: =SUM(G46:G51) -> 0 | K52: =SUM(K46:K51) -> 0 | L52: =SUM(L46:L51) -> 0 | M52: =SUM(M46:M51) -> 0 | N52: =SUM(N46:N51) -> 0 | O52: =SUM(O46:O51) -> 0 | P52: =SUM(P46:P51) -> 0 | Q52: =SUM(Q46:Q51) -> 0 | R52: =SUM(R46:R51) -> 302.225 | ... X52: =SUM(X46:X51) -> 0
B53: PP&E | E53: =R53 -> 121.749 | F53: =V53 -> 150.573 | R53: 121.749 | S53: 122.473 | T53: 131.288 | U53: 145.084 | V53: 150.573
B54: Capitalized internal use-software | E54: =R54 -> 18.974 | F54: =V54 -> 21.475 | R54: 18.974 | S54: 19.783 | T54: 20.567 | U54: 21.062 | V54: 21.475
B55: Goodwill | E55: =R55 -> 136.349 | F55: =V55 -> 143.452 | R55: 136.349 | S55: 138.49 | T55: 138.644 | U55: 138.954 | V55: 143.452
B56: Intangible Asset | E56: =R56 -> 27.452 | F56: =V56 -> 26.633 | R56: 27.452 | S56: 27.764 | T56: 26.624 | U56: 25.537 | V56: 26.633
B57: Restricted Cash | E57: =R57 -> 5.348 | F57: =V57 -> 5.471 | R57: 5.348 | S57: 5.526 | T57: 5.527 | U57: 5.367 | V57: 5.471
B58: operating lease | E58: =R58 -> 19.752 | F58: =V58 -> 14.588 | R58: 19.752 | S58: 17.927 | T58: 16.099 | U58: 13.95 | V58: 14.588
B59: other | E59: =R59 -> 1.947 | F59: =V59 -> 8.132 | R59: 1.947 | S59: 1.615 | T59: 2.213 | U59: 1.963 | V59: 8.132
B60: Total Assets | C60: =SUM(C52:C59) -> 0 | D60: =SUM(D52:D59) -> 0 | E60: =SUM(E52:E59) -> 633.796 | F60: =SUM(F52:F59) -> 1145.686 | G60: =SUM(G52:G59) -> 0 | K60: =SUM(K52:K59) -> 0 | L60: =SUM(L52:L59) -> 0 | M60: =SUM(M52:M59) -> 0 | N60: =SUM(N52:N59) -> 0 | O60: =SUM(O52:O59) -> 0 | P60: =SUM(P52:P59) -> 0 | Q60: =SUM(Q52:Q59) -> 0 | R60: =SUM(R52:R59) -> 633.796 | ... X60: =SUM(X52:X59) -> 0
B61: AP | E61: =R61 -> 2.604 | F61: =V61 -> 10.612 | R61: 2.604 | S61: 4.097 | T61: 11.053 | U61: 3.448 | V61: 10.612
B62: Accrued and other current | E62: =R62 -> 42.6 | F62: =V62 -> 55.874 | R62: 42.6 | S62: 28.823 | T62: 32.443 | U62: 28.652 | V62: 55.874
B63: Deferred revenue | E63: =R63 -> 82.275 | F63: =V63 -> 220.572 | R63: 82.275 | S63: 108.336 | T63: 148.006 | U63: 145.857 | V63: 220.572
B64: Liab from stock options | E64: =R64 -> 5.378 | F64: =V64 -> 1.793 | R64: 5.378 | S64: 4.482 | T64: 3.586 | U64: 2.689 | V64: 1.793
B65: operating lease | E65: =R65 -> 9.221 | F65: =V65 -> 7.296 | R65: 9.221 | S65: 8.816 | T65: 8.403 | U65: 7.943 | V65: 7.296
B66: warrant liab | E66: =R66 -> 0 | F66: =V66 -> 173.308 | R66: 0 | V66: 173.308
B67: Total Current Liabilities | C67: =SUM(C61:C66) -> 0 | D67: =SUM(D61:D66) -> 0 | E67: =SUM(E61:E66) -> 142.078 | F67: =SUM(F61:F66) -> 469.455 | G67: =SUM(G61:G66) -> 0 | K67: =SUM(K61:K66) -> 0 | L67: =SUM(L61:L66) -> 0 | M67: =SUM(M61:M66) -> 0 | N67: =SUM(N61:N66) -> 0 | O67: =SUM(O61:O66) -> 0 | P67: =SUM(P61:P66) -> 0 | Q67: =SUM(Q61:Q66) -> 0 | R67: =SUM(R61:R66) -> 142.078 | ... X67: =SUM(X61:X66) -> 0
B68: Deferred revenue | E68: =R68 -> 11.182 | F68: =V68 -> 27.522 | R68: 11.182 | S68: 29.676 | T68: 25.013 | U68: 48.332 | V68: 27.522
B69: deferred hosting costs | E69: =R69 -> 5.368 | F69: =V69 -> 4.034 | R69: 5.368 | S69: 7.75 | T69: 6.512 | U69: 5.273 | V69: 4.034
B70: warrant liab | E70: =R70 -> 18.077 | F70: =V70 -> 0 | R70: 18.077 | S70: 7.69 | T70: 13.369 | U70: 56.82 | V70: 0
B71: operating lease | E71: =R71 -> 12.392 | F71: =V71 -> 8.3 | R71: 12.392 | S71: 10.806 | T71: 9.139 | U71: 7.209 | V71: 8.3
B72: contingent considerations | E72: =R72 -> 2.883 | F72: =V72 -> 0 | R72: 2.883 | S72: 2.697 | T72: 2.774 | U72: 3.601 | V72: 0
B73: convertible notes | E73: =R73 -> 0 | F73: =V73 -> 446.884 | U73: 446.201 | V73: 446.884
B74: other | E74: =R74 -> 0.53 | F74: =V74 -> 1.06 | R74: 0.53 | S74: 0.415 | T74: 0.438 | U74: 0.477 | V74: 1.06
B75: Total Liablities | C75: =SUM(C67:C74) -> 0 | D75: =SUM(D67:D74) -> 0 | E75: =SUM(E67:E74) -> 192.51 | F75: =SUM(F67:F74) -> 957.255 | G75: =SUM(G67:G74) -> 0 | K75: =SUM(K67:K74) -> 0 | L75: =SUM(L67:L74) -> 0 | M75: =SUM(M67:M74) -> 0 | N75: =SUM(N67:N74) -> 0 | O75: =SUM(O67:O74) -> 0 | P75: =SUM(P67:P74) -> 0 | Q75: =SUM(Q67:Q74) -> 0 | R75: =SUM(R67:R74) -> 192.51 | ... X75: =SUM(X67:X74) -> 0
B76: Equity | C76: =C60-C75 -> 0 | D76: =D60-D75 -> 0 | E76: =E60-E75 -> 441.286 | F76: =F60-F75 -> 188.431 | G76: =G60-G75 -> 0 | K76: =K60-K75 -> 0 | L76: =L60-L75 -> 0 | M76: =M60-M75 -> 0 | N76: =N60-N75 -> 0 | O76: =O60-O75 -> 0 | P76: =P60-P75 -> 0 | Q76: =Q60-Q75 -> 0 | R76: =R60-R75 -> 441.286 | ... X76: =X60-X75 -> 0
B78: Interest Rate debt

Sheet Analysts
B1: 45413 | C1: 45444 | D1: 45474 | E1: 45505 | F1: 45536 | G1: 45566 | H1: 45597 | I1: 45627 | J1: 45658 | K1: 45689 | L1: 45717 | M1: 45748 | N1: 45778 | O1: 45809 | P1: 45839 | Q1: 45870 | R1: 45901 | S1: 45931 | T1: 45962 | U1: 45992 | V1: 46023 | W1: 46054 | X1: 46082 | Y1: 46113
A2: Sell | B2: 0 | C2: 0 | D2: 0 | E2: 0 | F2: 0 | G2: 0 | H2: 0 | I2: 0 | J2: 0 | K2: 0 | L2: 0 | M2: 0 | N2: 0 | O2: 0 | P2: 0 | Q2: 0 | R2: 0 | S2: 0 | T2: 0 | U2: 0 | V2: 2 | W2: 2 | X2: 1
A3: Hold | B3: 1 | C3: 1 | D3: 1 | E3: 1 | F3: 1 | G3: 1 | H3: 1 | I3: 1 | J3: 1 | K3: 0 | L3: 1 | M3: 1 | N3: 1 | O3: 1 | P3: 1 | Q3: 1 | R3: 1 | S3: 1 | T3: 2 | U3: 2 | V3: 3 | W3: 3 | X3: 4
A4: Buy | B4: 6 | C4: 6 | D4: 6 | E4: 6 | F4: 7 | G4: 6 | H4: 6 | I4: 6 | J4: 7 | K4: 10 | L4: 10 | M4: 10 | N4: 9 | O4: 9 | P4: 9 | Q4: 9 | R4: 9 | S4: 9 | T4: 8 | U4: 8 | V4: 7 | W4: 7 | X4: 6
A5: Strong buy | B5: 0 | C5: 0 | D5: 0 | E5: 0 | F5: 0 | G5: 0 | H5: 0 | I5: 0 | J5: 0 | K5: 0 | L5: 0 | M5: 0 | N5: 0 | O5: 0 | P5: 0 | Q5: 0 | R5: 0 | S5: 0 | T5: 0 | U5: 0 | V5: 0 | W5: 0 | X5: 0
A8: Price Targets
A9: Share Price | B9: 1.85 | C9: 1.91 | D9: 1.9 | E9: 2.24 | F9: 2.41 | G9: 2.19 | H9: 2.44 | I9: 3.8 | J9: 4.04 | K9: 5.54 | L9: 4.68 | M9: 3.53 | N9: 3.44 | O9: 4.52 | P9: 6.02 | Q9: 6.54 | R9: 7.59 | S9: 13.31 | T9: 12.84 | U9: 13.13 | V9: 21.38 | W9: 24.7 | X9: 24.5
A10: Consensus | B10: 4.68 | C10: 4.68 | D10: 4.3 | E10: 4.3 | F10: 4.39 | G10: 3.93 | H10: 3.93 | I10: 3.93 | J10: 4.33 | K10: 5.64 | L10: 6.27 | M10: 6.27 | N10: 5.98 | O10: 5.98 | P10: 6.71 | Q10: 6.86 | R10: 6.86 | S10: 7.56 | T10: 11.26 | U10: 11.26 | V10: 14.74 | W10: 20.64 | X10: 21.88

Sheet Model-graph
A1: Main

Sheet KPIs
B1: fy23 | C1: fy24 | D1: fy25 | E1: fy26
A2: Backlog | B2: 280 | C2: 242 | D2: 504 | E2: 900

Sheet Catalysts
A1: Main | B1: Date | C1: Close
E2: Date | F2: Event | M2: Earnings
E3: 45328 | F3: xxx
E4: 45302 | F4: xxx

Sheet DoR
A1: Main | B1: Date | C1: Price | D1: w/w | H1: Close to Close Weekly returns
B2: 2026-04-27 | C2: 36.9 | D2: =C2/C3-1 -> 0.041196388
B3: 2026-04-20 | C3: 35.44 | D3: =C3/C4-1 -> -0.079002079 | H3: Intervals | I3: Bin | J3: Frequency | K3: Range | L3: Probability | M3: Cumulative Percentage
B4: 2026-04-13 | C4: 38.48 | D4: =C4/C5-1 -> 0.10989328 | H4: =$I$19-3*$I$23 -> -0.30926341 | I4: =H4 -> -0.30926341 | J4: =COUNTIF(D:D,"<="&H4) -> 2 | K4: ="Less than "&TEXT(H4,"0,00%") -> Less than -30,93% | L4: =J4/$I$31 -> 0.0076628352 | M4: =L4 -> 0.0076628352
B5: 2026-04-06 | C5: 34.67 | D5: =C5/C6-1 -> -0.033723523 | H5: =$I$19-2.4*$I$23 -> -0.24533277 | I5: =H5 -> -0.24533277 | J5: =COUNTIFS(D:D,"<="&H5,D:D,">"&H4) -> 1 | K5: =TEXT(H4,"0,00%")&" to "&TEXT(H5,"0,00%") -> -30,93% to -24,53% | L5: =J5/$I$31 -> 0.0038314176 | M5: =M4+L5 -> 0.011494253
B6: 2026-03-30 | C6: 35.88 | D6: =C6/C7-1 -> 0.16267012 | H6: =$I$19-1.8*$I$23 -> -0.18140212 | I6: =H6 -> -0.18140212 | J6: =COUNTIFS(D:D,"<="&H6,D:D,">"&H5) -> 0 | K6: =TEXT(H5,"0,00%")&" to "&TEXT(H6,"0,00%") -> -24,53% to -18,14% | L6: =J6/$I$31 -> 0 | M6: =M5+L6 -> 0.011494253
B7: 2026-03-23 | C7: 30.86 | D7: =C7/C8-1 -> -0.087791901 | H7: =$I$19-1.2*$I$23 -> -0.11747147 | I7: =H7 -> -0.11747147 | J7: =COUNTIFS(D:D,"<="&H7,D:D,">"&H6) -> 18 | K7: =TEXT(H6,"0,00%")&" to "&TEXT(H7,"0,00%") -> -18,14% to -11,75% | L7: =J7/$I$31 -> 0.068965517 | M7: =M6+L7 -> 0.08045977
B8: 2026-03-16 | C8: 33.83 | D8: =C8/C9-1 -> 0.36466317 | H8: =$I$19-0.6*$I$23 -> -0.053540825 | I8: =H8 -> -0.053540825 | J8: =COUNTIFS(D:D,"<="&H8,D:D,">"&H7) -> 38 | K8: =TEXT(H7,"0,00%")&" to "&TEXT(H8,"0,00%") -> -11,75% to -5,35% | L8: =J8/$I$31 -> 0.14559387 | M8: =M7+L8 -> 0.22605364
B9: 2026-03-09 | C9: 24.79 | D9: =C9/C10-1 -> -0.019382911 | H9: =$I$19 -> 0.010389823 | I9: =H9 -> 0.010389823 | J9: =COUNTIFS(D:D,"<="&H9,D:D,">"&H8) -> 95 | K9: =TEXT(H8,"0,00%")&" to "&TEXT(H9,"0,00%") -> -5,35% to 1,04% | L9: =J9/$I$31 -> 0.36398467 | M9: =M8+L9 -> 0.59003831
B10: 2026-03-02 | C10: 25.28 | D10: =C10/C11-1 -> 0.047224524 | H10: =$I$19+0.6*$I$23 -> 0.07432047 | I10: =H10 -> 0.07432047 | J10: =COUNTIFS(D:D,"<="&H10,D:D,">"&H9) -> 57 | K10: =TEXT(H9,"0,00%")&" to "&TEXT(H10,"0,00%") -> 1,04% to 7,43% | L10: =J10/$I$31 -> 0.2183908 | M10: =M9+L10 -> 0.80842912
B11: 2026-02-23 | C11: 24.14 | D11: =C11/C12-1 -> 0.010041841 | H11: =$I$19+1.2*$I$23 -> 0.13825112 | I11: =H11 -> 0.13825112 | J11: =COUNTIFS(D:D,"<="&H11,D:D,">"&H10) -> 33 | K11: =TEXT(H10,"0,00%")&" to "&TEXT(H11,"0,00%") -> 7,43% to 13,83% | L11: =J11/$I$31 -> 0.12643678 | M11: =M10+L11 -> 0.9348659
B12: 2026-02-17 | C12: 23.9 | D12: =C12/C13-1 -> 0.066012489 | H12: =$I$19+1.8*$I$23 -> 0.20218177 | I12: =H12 -> 0.20218177 | J12: =COUNTIFS(D:D,"<="&H12,D:D,">"&H11) -> 6 | K12: =TEXT(H11,"0,00%")&" to "&TEXT(H12,"0,00%") -> 13,83% to 20,22% | L12: =J12/$I$31 -> 0.022988506 | M12: =M11+L12 -> 0.95785441
B13: 2026-02-09 | C13: 22.42 | D13: =C13/C14-1 -> 0.0071877808 | H13: =$I$19+2.4*$I$23 -> 0.26611241 | I13: =H13 -> 0.26611241 | J13: =COUNTIFS(D:D,"<="&H13,D:D,">"&H12) -> 4 | K13: =TEXT(H12,"0,00%")&" to "&TEXT(H13,"0,00%") -> 20,22% to 26,61% | L13: =J13/$I$31 -> 0.01532567 | M13: =M12+L13 -> 0.97318008
B14: 2026-02-02 | C14: 22.26 | D14: =C14/C15-1 -> -0.10853024 | H14: =$I$19+3*$I$23 -> 0.33004306 | I14: =H14 -> 0.33004306 | J14: =COUNTIFS(D:D,"<="&H14,D:D,">"&H13) -> 2 | K14: =TEXT(H13,"0,00%")&" to "&TEXT(H14,"0,00%") -> 26,61% to 33,00% | L14: =J14/$I$31 -> 0.0076628352 | M14: =M13+L14 -> 0.98084291
B15: 2026-01-26 | C15: 24.97 | D15: =C15/C16-1 -> -0.073125464 | I15: More | J15: =COUNTIF(D:D,">"&H14) -> 5 | K15: ="Greater than "&TEXT(H14,"0,00%") -> Greater than 33,00% | L15: =J15/$I$31 -> 0.019157088 | M15: =M14+L15 -> 1
B16: 2026-01-20 | C16: 26.94 | D16: =C16/C17-1 -> -0.063933287
B17: 2026-01-12 | C17: 28.78 | D17: =C17/C18-1 -> 0.26728314 | H17: Descriptive Statistics
B18: 2026-01-05 | C18: 22.71 | D18: =C18/C19-1 -> 0.11268986
B19: 2025-12-29 | C19: 20.41 | D19: =C19/C20-1 -> 0.054235537 | H19: Mean | I19: =AVERAGE(D:D) -> 0.010389823
B20: 2025-12-22 | C20: 19.36 | D20: =C20/C21-1 -> 0.0093847758 | H20: Standard Error | I20: =_xlfn.STDEV.S(D:D)/SQRT(COUNT(D:D)) -> 0.0065953462
B21: 2025-12-15 | C21: 19.18 | D21: =C21/C22-1 -> 0.051535088 | H21: Median | I21: =MEDIAN(D:D) -> 0.0015151515
B22: 2025-12-08 | C22: 18.24 | D22: =C22/C23-1 -> 0.42834769 | H22: Mode | I22: =MODE(D:D) -> 0
B23: 2025-12-01 | C23: 12.77 | D23: =C23/C24-1 -> 0.073109244 | H23: Standard Deviation | I23: =_xlfn.STDEV.S(D:D) -> 0.10655108
B24: 2025-11-24 | C24: 11.9 | D24: =C24/C25-1 -> 0.066308244 | H24: Sample Variance | I24: =_xlfn.VAR.S(D:D) -> 0.011353132
B25: 2025-11-17 | C25: 11.16 | D25: =C25/C26-1 -> -0.021052632 | H25: Kurtosis | I25: =KURT(D:D) -> 5.3654859
B26: 2025-11-10 | C26: 11.4 | D26: =C26/C27-1 -> -0.11007026 | H26: Skewness | I26: =SKEW(D:D) -> 1.1659371
B27: 2025-11-03 | C27: 12.81 | D27: =C27/C28-1 -> -0.047583643 | H27: Range | I27: =I29-I28 -> 0.8591233
B28: 2025-10-27 | C28: 13.45 | D28: =C28/C29-1 -> -0.011756062 | H28: Minimum | I28: =MIN(D:D) -> -0.33828996
B29: 2025-10-20 | C29: 13.61 | D29: =C29/C30-1 -> 0.038138825 | H29: Maximum | I29: =MAX(D:D) -> 0.52083333
B30: 2025-10-13 | C30: 13.11 | D30: =C30/C31-1 -> -0.10816327 | H30: Sum | I30: =SUM(D:D) -> 2.7117438
B31: 2025-10-06 | C31: 14.7 | D31: =C31/C32-1 -> -0.03984324 | H31: Count | I31: =COUNT(D:D) -> 261
B32: 2025-09-29 | C32: 15.31 | D32: =C32/C33-1 -> 0.25491803
B33: 2025-09-22 | C33: 12.2 | D33: =C33/C34-1 -> 0.098109811 | I33: Average Returns | J33: Count | K33: Frequency % | L33: Frequency Adjusted Return
B34: 2025-09-15 | C34: 11.11 | D34: =C34/C35-1 -> 0.13599182 | H34: Positive Data Points | I34: =AVERAGEIF(D:D,">0") -> 0.078784177 | J34: =COUNTIF(D:D,">0") -> 135 | K34: =J34/$I$31 -> 0.51724138 | L34: =K34*I34 -> 0.040750437
B35: 2025-09-08 | C35: 9.78 | D35: =C35/C36-1 -> 0.49770291 | H35: Negative Data Points | I35: =AVERAGEIF(D:D,"<0") -> -0.064951804 | J35: =COUNTIF(D:D,"<0") -> 122 | K35: =J35/$I$31 -> 0.46743295 | L35: =K35*I35 -> -0.030360614
B36: 2025-09-02 | C36: 6.53 | D36: =C36/C37-1 -> -0.078984485 | H36: Zero | I36: 0 | J36: =COUNTIF(D:D,"0") -> 4 | K36: =J36/$I$31 -> 0.01532567 | L36: =K36*I36 -> 0
B37: 2025-08-25 | C37: 7.09 | D37: =C37/C38-1 -> 0.042647059
B38: 2025-08-18 | C38: 6.8 | D38: =C38/C39-1 -> 0.0029498525 | H38: Std Dev | I38: Upper Bound | J38: Lower Bound | K38: Actual Count | L38: Actual % Count | M38: Normal % Count
B39: 2025-08-11 | C39: 6.78 | D39: =C39/C40-1 -> 0.059375 | H39: 1 | I39: =$I$19+($H39*$I$23) -> 0.1169409 | J39: =$I$19-($H39*$I$23) -> -0.096161256 | K39: =COUNTIFS(D:D,"<"&I39,D:D,">"&J39) -> 211 | L39: =K39/$I$31 -> 0.80842912 | M39: 0.6827
B40: 2025-08-04 | C40: 6.4 | D40: =C40/C41-1 -> 0.035598706 | H40: 2 | I40: =$I$19+($H40*$I$23) -> 0.22349198 | J40: =$I$19-($H40*$I$23) -> -0.20271234 | K40: =COUNTIFS(D:D,"<"&I40,D:D,">"&J40) -> 250 | L40: =K40/$I$31 -> 0.95785441 | M40: 0.9545
B41: 2025-07-28 | C41: 6.18 | D41: =C41/C42-1 -> -0.070676692 | H41: 3 | I41: =$I$19+($H41*$I$23) -> 0.33004306 | J41: =$I$19-($H41*$I$23) -> -0.30926341 | K41: =COUNTIFS(D:D,"<"&I41,D:D,">"&J41) -> 254 | L41: =K41/$I$31 -> 0.97318008 | M41: 0.9973
B42: 2025-07-21 | C42: 6.65 | D42: =C42/C43-1 -> -0.020618557
B43: 2025-07-14 | C43: 6.79 | D43: =C43/C44-1 -> 0.10586319 | H43: Percentiles
B44: 2025-07-07 | C44: 6.14 | D44: =C44/C45-1 -> -0.10364964 | H44: 0.01 | I44: =_xlfn.PERCENTILE.INC(D:D,H44) -> -0.2164678 | J44: 0.2 | K44: =_xlfn.PERCENTILE.INC(D:D,J44) -> -0.063314711 | L44: 0.85 | M44: =_xlfn.PERCENTILE.INC(D:D,L44) -> 0.087378641
B45: 2025-06-30 | C45: 6.85 | D45: =C45/C46-1 -> 0.12850082 | H45: 0.02 | I45: =_xlfn.PERCENTILE.INC(D:D,H45) -> -0.17619331 | J45: 0.25 | K45: =_xlfn.PERCENTILE.INC(D:D,J45) -> -0.044117647 | L45: 0.86 | M45: =_xlfn.PERCENTILE.INC(D:D,L45) -> 0.092300054
B46: 2025-06-23 | C46: 6.07 | D46: =C46/C47-1 -> 0.20675944 | H46: 0.03 | I46: =_xlfn.PERCENTILE.INC(D:D,H46) -> -0.15278825 | J46: 0.3 | K46: =_xlfn.PERCENTILE.INC(D:D,J46) -> -0.033723523 | L46: 0.87 | M46: =_xlfn.PERCENTILE.INC(D:D,L46) -> 0.097882832
B47: 2025-06-16 | C47: 5.03 | D47: =C47/C48-1 -> -0.063314711 | H47: 0.04 | I47: =_xlfn.PERCENTILE.INC(D:D,H47) -> -0.13712532 | J47: 0.35 | K47: =_xlfn.PERCENTILE.INC(D:D,J47) -> -0.019855596 | L47: 0.88 | M47: =_xlfn.PERCENTILE.INC(D:D,L47) -> 0.10229441
B48: 2025-06-09 | C48: 5.37 | D48: =C48/C49-1 -> -0.080479452 | H48: 0.05 | I48: =_xlfn.PERCENTILE.INC(D:D,H48) -> -0.12682927 | J48: 0.4 | K48: =_xlfn.PERCENTILE.INC(D:D,J48) -> -0.010752688 | L48: 0.89 | M48: =_xlfn.PERCENTILE.INC(D:D,L48) -> 0.1046503
B49: 2025-06-02 | C49: 5.84 | D49: =C49/C50-1 -> 0.52083333 | H49: 0.06 | I49: =_xlfn.PERCENTILE.INC(D:D,H49) -> -0.12040827 | J49: 0.45 | K49: =_xlfn.PERCENTILE.INC(D:D,J49) -> -0.003033367 | L49: 0.9 | M49: =_xlfn.PERCENTILE.INC(D:D,L49) -> 0.10989328
B50: 2025-05-27 | C50: 3.84 | D50: =C50/C51-1 -> 0.043478261 | H50: 0.07 | I50: =_xlfn.PERCENTILE.INC(D:D,H50) -> -0.11977407 | J50: 0.5 | K50: =_xlfn.PERCENTILE.INC(D:D,J50) -> 0.0015151515 | L50: 0.91 | M50: =_xlfn.PERCENTILE.INC(D:D,L50) -> 0.11496231
B51: 2025-05-19 | C51: 3.68 | D51: =C51/C52-1 -> -0.063613232 | H51: 0.08 | I51: =_xlfn.PERCENTILE.INC(D:D,H51) -> -0.11181431 | J51: 0.55 | K51: =_xlfn.PERCENTILE.INC(D:D,J51) -> 0.0075642965 | L51: 0.92 | M51: =_xlfn.PERCENTILE.INC(D:D,L51) -> 0.1199912
B52: 2025-05-12 | C52: 3.93 | D52: =C52/C53-1 -> 0.10393258 | H52: 0.09 | I52: =_xlfn.PERCENTILE.INC(D:D,H52) -> -0.10635781 | J52: 0.6 | K52: =_xlfn.PERCENTILE.INC(D:D,J52) -> 0.013435701 | L52: 0.93 | M52: =_xlfn.PERCENTILE.INC(D:D,L52) -> 0.12999269
B53: 2025-05-05 | C53: 3.56 | D53: =C53/C54-1 -> 0.014245014 | H53: 0.1 | I53: =_xlfn.PERCENTILE.INC(D:D,H53) -> -0.10227273 | J53: 0.65 | K53: =_xlfn.PERCENTILE.INC(D:D,J53) -> 0.026548673 | L53: 0.94 | M53: =_xlfn.PERCENTILE.INC(D:D,L53) -> 0.15759141
B54: 2025-04-28 | C54: 3.51 | D54: =C54/C55-1 -> 0.03539823 | H54: 0.11 | I54: =_xlfn.PERCENTILE.INC(D:D,H54) -> -0.089289392 | J54: 0.7 | K54: =_xlfn.PERCENTILE.INC(D:D,J54) -> 0.042647059 | L54: 0.95 | M54: =_xlfn.PERCENTILE.INC(D:D,L54) -> 0.18309859
B55: 2025-04-21 | C55: 3.39 | D55: =C55/C56-1 -> 0.049535604 | H55: 0.12 | I55: =_xlfn.PERCENTILE.INC(D:D,H55) -> -0.086918897 | J55: 0.75 | K55: =_xlfn.PERCENTILE.INC(D:D,J55) -> 0.058524173 | L55: 0.96 | M55: =_xlfn.PERCENTILE.INC(D:D,L55) -> 0.20323655
B56: 2025-04-14 | C56: 3.23 | D56: =C56/C57-1 -> 0.018927445 | H56: 0.13 | I56: =_xlfn.PERCENTILE.INC(D:D,H56) -> -0.085099528 | J56: 0.8 | K56: =_xlfn.PERCENTILE.INC(D:D,J56) -> 0.071823204 | L56: 0.97 | M56: =_xlfn.PERCENTILE.INC(D:D,L56) -> 0.21964032
B57: 2025-04-07 | C57: 3.17 | D57: =C57/C58-1 -> 0 | H57: 0.14 | I57: =_xlfn.PERCENTILE.INC(D:D,H57) -> -0.082480798 | L57: 0.98 | M57: =_xlfn.PERCENTILE.INC(D:D,L57) -> 0.2831596
B58: 2025-03-31 | C58: 3.17 | D58: =C58/C59-1 -> -0.083815029 | H58: 0.15 | I58: =_xlfn.PERCENTILE.INC(D:D,H58) -> -0.078984485 | L58: 0.99 | M58: =_xlfn.PERCENTILE.INC(D:D,L58) -> 0.42578934
B59: 2025-03-24 | C59: 3.46 | D59: =C59/C60-1 -> -0.08707124
B60: 2025-03-17 | C60: 3.79 | D60: =C60/C61-1 -> -0.088942308 | H60: Stop % | I60: 0.1
B61: 2025-03-10 | C61: 4.16 | D61: =C61/C62-1 -> 0.045226131 | H61: Target % | I61: 0.3
B62: 2025-03-03 | C62: 3.98 | D62: =C62/C63-1 -> -0.13852814
B63: 2025-02-24 | C63: 4.62 | D63: =C63/C64-1 -> -0.070422535 | H63: Current Price | I63: 33.5
B64: 2025-02-18 | C64: 4.97 | D64: =C64/C65-1 -> -0.17986799 | H64: Stop Price | I64: =I63*(1-I60) -> 30.15
B65: 2025-02-10 | C65: 6.06 | D65: =C65/C66-1 -> 0.01 | H65: Target Price | I65: =I63*(1+I61) -> 43.55
B66: 2025-02-03 | C66: 6 | D66: =C66/C67-1 -> -0.016393443
B67: 2025-01-27 | C67: 6.1 | D67: =C67/C68-1 -> 0.12132353
B68: 2025-01-21 | C68: 5.44 | D68: =C68/C69-1 -> 0.42408377
B69: 2025-01-13 | C69: 3.82 | D69: =C69/C70-1 -> 0.029649596
B70: 2025-01-06 | C70: 3.71 | D70: =C70/C71-1 -> -0.12085308
B71: 2024-12-30 | C71: 4.22 | D71: =C71/C72-1 -> -0.03652968
B72: 2024-12-23 | C72: 4.38 | D72: =C72/C73-1 -> 0.084158416
B73: 2024-12-16 | C73: 4.04 | D73: =C73/C74-1 -> 0.0074812968
B74: 2024-12-09 | C74: 4.01 | D74: =C74/C75-1 -> -0.036057692
B75: 2024-12-02 | C75: 4.16 | D75: =C75/C76-1 -> 0.058524173
B76: 2024-11-25 | C76: 3.93 | D76: =C76/C77-1 -> 0.11965812
B77: 2024-11-18 | C77: 3.51 | D77: =C77/C78-1 -> 0.19795222
... B262: 2021-05-03 | C262: 9.82 | D262: =C262/C263-1 -> -0.010080645
B263: 2021-04-26 | C263: 9.92
